setup.cfg
setup.py
webdriver_components/__init__.py
webdriver_components/conftest.py
webdriver_components/pageobjects.py
webdriver_components/tablerow.py
webdriver_components/test_webdriver_elements.py
webdriver_components/testutils.py
webdriver_components/utils.py
webdriver_components_py2.egg-info/PKG-INFO
webdriver_components_py2.egg-info/SOURCES.txt
webdriver_components_py2.egg-info/dependency_links.txt
webdriver_components_py2.egg-info/requires.txt
webdriver_components_py2.egg-info/top_level.txt