Metadata-Version: 1.1
Name: webdriver-components-py2
Version: 0.0.5
Summary: Webdriver_components
Home-page: https://github.com/amagee/webdriver-components
Author: Andrew Magee
Author-email: amagee@gmail.com
License: Apache License, Version 2.0
Keywords: selenium webdriver testing page objects components
Platform: UNKNOWN
Classifier: Development Status :: 3 - Alpha
Classifier: License :: OSI Approved :: Apache Software License
Classifier: Programming Language :: Python :: 3
Classifier: Programming Language :: Python :: 3.5
Classifier: Programming Language :: Python :: 3.6
Classifier: Programming Language :: Python :: 3 :: Only
Classifier: Topic :: Utilities
Classifier: Topic :: Software Development :: Testing
